odoo/addons/sale_cancel_confirm/README.rst
odoo/addons/sale_cancel_confirm/__init__.py
odoo/addons/sale_cancel_confirm/__manifest__.py
odoo/addons/sale_cancel_confirm/i18n/es.po
odoo/addons/sale_cancel_confirm/i18n/it.po
odoo/addons/sale_cancel_confirm/i18n/sale_cancel_confirm.pot
odoo/addons/sale_cancel_confirm/model/__init__.py
odoo/addons/sale_cancel_confirm/model/sale.py
odoo/addons/sale_cancel_confirm/readme/CONTRIBUTORS.rst
odoo/addons/sale_cancel_confirm/readme/DESCRIPTION.rst
odoo/addons/sale_cancel_confirm/static/description/icon.png
odoo/addons/sale_cancel_confirm/static/description/index.html
odoo14_addon_sale_cancel_confirm-14.0.1.0.1.dev8.dist-info/METADATA
odoo14_addon_sale_cancel_confirm-14.0.1.0.1.dev8.dist-info/WHEEL
odoo14_addon_sale_cancel_confirm-14.0.1.0.1.dev8.dist-info/top_level.txt
odoo14_addon_sale_cancel_confirm-14.0.1.0.1.dev8.dist-info/RECORD
